spin/__init__.py
spin/exceptions.py
spin/helpers.py
spin/spin.py
spin/types.py
spin/object_mapping/__init__.py
spin/object_mapping/object_mapping.json
spin_dataset_api-1.0.0.dist-info/LICENSE
spin_dataset_api-1.0.0.dist-info/METADATA
spin_dataset_api-1.0.0.dist-info/WHEEL
spin_dataset_api-1.0.0.dist-info/top_level.txt
spin_dataset_api-1.0.0.dist-info/RECORD
