Metadata-Version: 2.1
Name: spin-dataset-api
Version: 1.0.0
Summary: A description of your package
Home-page: https://github.com/joshmyersdean/spin-api
Author: Josh Myers-Dean
Author-email: josh.myers-dean@colorado.edu
Classifier: Programming Language :: Python :: 3
Classifier: License :: OSI Approved :: MIT License
Classifier: Operating System :: OS Independent
Requires-Python: >=3.6
License-File: LICENSE
Requires-Dist: numpy
Requires-Dist: requests
Requires-Dist: pillow
Requires-Dist: matplotlib
Requires-Dist: pycocotools
Requires-Dist: opencv-python
Requires-Dist: tqdm
